omigo_ext/__init__.py
omigo_ext/etl_ext.py
omigo_ext/geomap_viz.py
omigo_ext/graph_ext.py
omigo_ext/graphviz_ext.py
omigo_ext/jira_ext.py
omigo_ext/kafka_ext.py
omigo_ext/logscale_ext.py
omigo_ext/multithread_ext.py
omigo_ext/presto_ext.py
omigo_ext/spark_ext.py
omigo_ext/splunk_ext.py
omigo_ext/sql_helper.py
omigo_ext/stats.py
omigo_ext/ws_ext.py
omigo_ext-0.9.2.dist-info/METADATA
omigo_ext-0.9.2.dist-info/WHEEL
omigo_ext-0.9.2.dist-info/top_level.txt
omigo_ext-0.9.2.dist-info/RECORD
