Metadata-Version: 2.4
Name: omigo_ext
Version: 0.9.2
Summary: Extensions for omigo_core package
Home-page: https://github.com/CrowdStrike/omigo-data-analytics
Author: amit jaiswal
Author-email: amit.jaiswal@gmail.com
Project-URL: Bug Tracker, https://github.com/CrowdStrike/omigo-data-analytics/browse
Classifier: Programming Language :: Python :: 3
Classifier: License :: OSI Approved :: MIT License
Classifier: Operating System :: OS Independent
Requires-Python: >=3.6
Requires-Dist: numpy
Requires-Dist: pandas
Requires-Dist: statistics
Requires-Dist: matplotlib
Requires-Dist: seaborn
Requires-Dist: omigo_core
Requires-Dist: kafka-python
Requires-Dist: google-api-python-client
Requires-Dist: graphviz
Requires-Dist: jira
Requires-Dist: bokeh
Requires-Dist: humiolib
Requires-Dist: pyspark
Requires-Dist: splunk-sdk
